kvcommon_flask/context.py
kvcommon_flask/exceptions.py
kvcommon_flask/headers.py
kvcommon_flask/metrics/__init__.py
kvcommon_flask/metrics/metrics.py
kvcommon_flask/middleware.py
kvcommon_flask/responses.py
kvcommon_flask/scheduler.py
kvcommon_flask/traces/__init__.py
kvcommon_flask-0.1.0.dist-info/LICENSE
kvcommon_flask-0.1.0.dist-info/METADATA
kvcommon_flask-0.1.0.dist-info/WHEEL
kvcommon_flask-0.1.0.dist-info/RECORD
