Metadata-Version: 2.1
Name: kvcommon-flask
Version: 0.1.0
Summary: Library of various Flask utils that aren't worthy of their own dedicated libs.
Home-page: https://github.com/RAVoigt/kvcommon-flask
Author: Rob Voigt
Author-email: code@ravoigt.com
Requires-Python: >=3.11,<4.0
Classifier: Programming Language :: Python :: 3
Classifier: Programming Language :: Python :: 3.11
Classifier: Programming Language :: Python :: 3.12
Classifier: Programming Language :: Python :: 3.13
Provides-Extra: metrics
Provides-Extra: scheduler
Provides-Extra: traces
Requires-Dist: flask-http-middleware (>=0.4.2,<0.5.0)
Requires-Dist: kvcommon (>=0.1.4,<0.2.0)
Requires-Dist: toml (>=0.10.2,<0.11.0)
Project-URL: Repository, https://github.com/RAVoigt/kvcommon-flask
